{"name":"metro","children":[{"name":"Station","children":[{"name":"Station  Bench Option","size":1000},{"name":"Station Linear","size":1000},{"name":"Station new","size":1000},{"name":"TSE - option 1","children":[{"name":"Access to Platform","children":[{"name":"Station Option 8","children":[{"name":"Station Option 8, WORKSHOP","size":1000}]},{"name":"Station Option 9","children":[{"name":"Station Option 9, WORKSHOP","size":1000}]},{"name":"Station Option 5, WORKSHOP","size":1000},{"name":"Lift option","size":1000},{"name":"Station option boomerang - option 1","children":[{"name":"Structure comments on boomerang","size":1000},{"name":"Services - Option 1","size":1000},{"name":"Adit extent clarification","size":1000}]},{"name":"Station option boomerang - option 2","children":[{"name":"Services - Option 2","size":1000}]}]}]},{"name":"TSE - option 2","size":1000},{"name":"TSE - option 3","size":1000}]},{"name":"Podium","children":[{"name":"Car Park above Ground","size":1000},{"name":"Car park below Ground","children":[{"name":"Carp Park Entry North East","children":[{"name":"Car Park","children":[{"name":"Car park Option - Double lanes ","children":[{"name":"Car park Option - Double lanes ","size":1000}]},{"name":"Car Park options - Single lanes","children":[{"name":"Car Park options - Single lanes","size":1000}]},{"name":"Car Park option  - Lift","children":[{"name":"Car Park option  - Lift","size":1000}]}]}]}]},{"name":"Podium Linear Lobby","size":1000},{"name":"Podium Park St Lobby","children":[{"name":"Secure Line","size":1000},{"name":"Entry Ramp - Park St - Option 1","size":1000},{"name":"Entry Ramp - Park St - Option 2","size":1000},{"name":"Entry Ramps at Castlereigh St","size":1000}]},{"name":"Podium Raised Lobby","size":1000},{"name":"End of Trip ","size":1000}]},{"name":"Tower","children":[{"name":"Lift Core compact","size":1000},{"name":"Lift Core Linear","size":1000},{"name":"West Core","size":1000},{"name":"Bench Core","children":[{"name":"Cruciform Core","children":[{"name":"East West Core","children":[{"name":"Core Layouts","children":[{"name":"Structural Review Core","children":[{"name":"First Pass Structure","children":[{"name":"Services Stacking - North","children":[{"name":"Core Toilet option 1","size":1000},{"name":"Core toilet option 2","size":1000}]},{"name":"Servcices Stacking - Pancake","size":1000},{"name":"Services and Structure Review Station","children":[{"name":"Structure Workshop","children":[{"name":"QS Issue","size":1000},{"name":"Structural Review","children":[{"name":"Structure review","children":[{"name":"Revised Structure - option 1","size":1000},{"name":"Revised Structure - option 2","children":[{"name":"Station Option 2","children":[{"name":"Station Option 2","children":[{"name":"Station Option 2","size":1000}]}]}]}]}]},{"name":"Floor plan update Mid level","size":1000}]},{"name":"Services diagrams","size":1000},{"name":"TES riser path","size":1000}]}]}]},{"name":"Goods Lift option 1","size":1000},{"name":"Goods Lift option 2","size":1000}]}]}]},{"name":"North South Core","children":[{"name":"North South Core , Common lobby","size":1000},{"name":"typical tower plans","size":1000},{"name":"North South Core","size":1000}]}]},{"name":"North Core","size":1000},{"name":"South Core","size":1000},{"name":"Tower envelope ANZ reverse","children":[{"name":"tower massing FSR 17 to 1","children":[{"name":"tower massing FSR 17 to 1","children":[{"name":"tower massing FSR 17 to 1, Shadow","children":[{"name":"Envelope Elevation Study","children":[{"name":"Street Elevation","children":[{"name":"Shadow impact, building envelope","size":1000},{"name":"Setbacks to building envelope - carve 1","children":[{"name":"Updated building form","children":[{"name":"Updated building form","children":[{"name":"Updated building form","children":[{"name":"Context Image update","size":1000},{"name":"Building Form - shaping","size":1000}]}]}]}]}]}]},{"name":"Context PhotoShop","size":1000}]}]}]}]},{"name":"Tower envelope solar access plane","children":[{"name":"tower massing FSR 11 to 1","children":[{"name":"tower massing FSR 11 to 1","children":[{"name":"tower massing FSR 11 to 1, Shadow","size":1000}]},{"name":"tower massing FSR 14 to 1","children":[{"name":"tower massing FSR 14 to 1, Shadow","children":[{"name":"Envelope Elevation Study","children":[{"name":"Street Elevation","size":1000}]},{"name":"Context PhotoShop","size":1000}]}]}]}]},{"name":"Tower max envelope","children":[{"name":"tower massing FSR 15 to 1","size":1000},{"name":"tower massing FSR 22 to 1","children":[{"name":"Tower massing FSR 15 to 1","children":[{"name":"Tower massing FSR 15 to 1, Shadow","size":1000}]},{"name":"tower massing FSR 22 to 1","children":[{"name":"tower massing FSR 22 to 1","children":[{"name":"tower massing FSR 22 to 1, Shadow","children":[{"name":"Envelope Elevation Study","size":1000},{"name":"Street Elevation","size":1000}]}]},{"name":"tower massing FSR 22 to 1, Shadow","children":[{"name":"Envelope Elevation Study","size":1000},{"name":"Context PhotoShop","children":[{"name":"Building Design - Carved Solid","children":[{"name":"Glazing Study - Opaque","size":1000},{"name":"Glazing Study - Transparent","size":1000},{"name":"Building Design study","size":1000},{"name":"renders","size":1000},{"name":"Setbacks to building envelope - carve 2","children":[{"name":"Street Elevation","children":[{"name":"Overshadowing Analysis","children":[{"name":"Mass renders","size":1000}]}]}]}]},{"name":"Building Design - Shifted Masses","children":[{"name":"Building Form ","children":[{"name":"Massing study - Option 1","size":1000},{"name":"Massing study - Option 2","size":1000}]}]}]},{"name":"tower massing FSR 17 to 1, push up","size":1000},{"name":"tower massing resindential only","size":1000}]}]}]},{"name":"tower massing FSR 37 to 1","children":[{"name":"tower massing FSR 37 to 1","children":[{"name":"tower massing FSR 37 to 1, Shadow","size":1000}]}]},{"name":"tower massing FSR 27 to 1","children":[{"name":"tower massing FSR 27 to 1","children":[{"name":"tower massing FSR 27 to 1, Shadow","size":1000}]}]}]},{"name":"tower massing FSR 22 to 1","size":1000},{"name":"Test Residential layouts","size":1000},{"name":"Test Residential layouts","size":1000},{"name":"Test Residential layouts","size":1000}]}]}
